{
  "project_info": {
    "project_number": "658511461471",
    "project_id": "firebase-socialnetworks"
  },
  "client": [
    {
      "client_info": {
        "mobilesdk_app_id": "1:658511461471:android:1dd4a99e144eeea7",
        "android_client_info": {
          "package_name": "com.flatstack.socialnetworks"
        }
      },
      "oauth_client": [
        {
          "client_id": "658511461471-5p2nii0h5n10fef03ccomttflnrs675b.apps.googleusercontent.com",
          "client_type": 1,
          "android_info": {
            "package_name": "com.flatstack.socialnetworks",
            "certificate_hash": "C23363C2A60BC12A6DC3D4B70C310C36F999D6A4"
          }
        },
        {
          "client_id": "658511461471-9kes67m8nuc9895uiuckuonfsgs39k4h.apps.googleusercontent.com",
          "client_type": 3
        }
      ],
      "api_key": [
        {
          "current_key": "AIzaSyColYESmZoG9EHDEBKm77gU-BjiMqJIizI"
        }
      ],
      "services": {
        "analytics_service": {
          "status": 1
        },
        "appinvite_service": {
          "status": 1,
          "other_platform_oauth_client": []
        },
        "ads_service": {
          "status": 1
        }
      }
    }
  ],
  "configuration_version": "1"
}